prettycm/__init__.py
prettycm/cm_object.py
prettycm/draw.py
prettycm/presets/__init__.py
prettycm/presets/meta.py
prettycm/presets/presets.py
prettycm/static/font/gmarket.ttf
prettycm/static/font/title.ttf
prettycm-1.2.8.dist-info/LICENSE
prettycm-1.2.8.dist-info/METADATA
prettycm-1.2.8.dist-info/WHEEL
prettycm-1.2.8.dist-info/top_level.txt
prettycm-1.2.8.dist-info/RECORD
