Metadata-Version: 2.1
Name: prettycm
Version: 1.2.8
Summary: Pretty Confusion matrix drawer, prettier than matplotlib
Home-page: https://github.com/KorKite/pretty-confusion-matrix
Author: KOJUNSEO
Author-email: sta06167@naver.com
License: UNKNOWN
Platform: UNKNOWN
Classifier: License :: OSI Approved :: MIT License
Requires-Dist: Pillow (>=9.0.1)
Requires-Dist: scikit-learn (==1.0.2)
Requires-Dist: numpy (>=1.21.5)
